st2flake8/__init__.py
st2flake8/license_rules.py
st2flake8/tests/__init__.py
st2flake8/tests/fixtures/__init__.py
st2flake8/tests/fixtures/loader.py
st2flake8/tests/unit/__init__.py
st2flake8/tests/unit/base.py
st2flake8/tests/unit/test_license_checker.py
st2flake8-0.2.0.dist-info/LICENSE
st2flake8-0.2.0.dist-info/METADATA
st2flake8-0.2.0.dist-info/WHEEL
st2flake8-0.2.0.dist-info/entry_points.txt
st2flake8-0.2.0.dist-info/top_level.txt
st2flake8-0.2.0.dist-info/RECORD
